graphene_django_cruddals/__init__.py
graphene_django_cruddals/main.py
graphene_django_cruddals/client/__init__.py
graphene_django_cruddals/client/build_functions.py
graphene_django_cruddals/converters/__init__.py
graphene_django_cruddals/converters/compat.py
graphene_django_cruddals/converters/converter_filter_input.py
graphene_django_cruddals/converters/converter_input.py
graphene_django_cruddals/converters/converter_input_relation_nested.py
graphene_django_cruddals/converters/converter_order_by_input.py
graphene_django_cruddals/converters/converter_output.py
graphene_django_cruddals/converters/utils.py
graphene_django_cruddals/resolvers/__init__.py
graphene_django_cruddals/resolvers/main.py
graphene_django_cruddals/scalars_type/__init__.py
graphene_django_cruddals/utils/__init__.py
graphene_django_cruddals/utils/decorators.py
graphene_django_cruddals/utils/main.py
graphene_django_cruddals/views/__init__.py
graphene_django_cruddals/views/cruddals_views.py
graphene_django_cruddals/views/file_upload_graphql_view.py
graphene_django_cruddals-0.1.24.dist-info/licenses/LICENSE
graphene_django_cruddals-0.1.24.dist-info/METADATA
graphene_django_cruddals-0.1.24.dist-info/WHEEL
graphene_django_cruddals-0.1.24.dist-info/top_level.txt
graphene_django_cruddals-0.1.24.dist-info/RECORD
