Metadata-Version: 2.4
Name: graphene_django_cruddals
Version: 0.1.24
Summary: Framework for trivial code, Easy and Fast for learn, Easy and Fast for use
Author-email: Juan J Cardona <juanjcardona13@gmail.com>
License: Apache 2.0
Project-URL: Homepage, https://github.com/juanjcardona13/graphene_django_cruddals
Keywords: api,graphql,crud,graphene,graphene-django,cruddals
Classifier: Development Status :: 3 - Alpha
Classifier: Intended Audience :: Developers
Classifier: Topic :: Software Development :: Libraries
Classifier: Programming Language :: Python :: 3
Classifier: Programming Language :: Python :: 3.6
Classifier: Programming Language :: Python :: 3.7
Classifier: Programming Language :: Python :: 3.8
Classifier: Programming Language :: Python :: 3.9
Classifier: Programming Language :: Python :: 3.10
Classifier: Programming Language :: Python :: Implementation :: PyPy
Classifier: Framework :: Django
Classifier: Framework :: Django :: 3.2
Classifier: Framework :: Django :: 4.2
Requires-Python: >=3.6
License-File: LICENSE
Requires-Dist: graphene-django>=3.0.0
Requires-Dist: graphene-cruddals>=0.2.13
Provides-Extra: test
Requires-Dist: pytest>=7.3.1; extra == "test"
Requires-Dist: pytest-cov; extra == "test"
Requires-Dist: pytest-random-order; extra == "test"
Requires-Dist: coveralls; extra == "test"
Requires-Dist: mock; extra == "test"
Requires-Dist: pytz; extra == "test"
Requires-Dist: django-filter>=22.1; extra == "test"
Requires-Dist: pytest-django>=4.5.2; extra == "test"
Provides-Extra: dev
Requires-Dist: ruff==0.1.2; extra == "dev"
Requires-Dist: pre-commit; extra == "dev"
Requires-Dist: pytest>=7.3.1; extra == "dev"
Requires-Dist: pytest-cov; extra == "dev"
Requires-Dist: pytest-random-order; extra == "dev"
Requires-Dist: coveralls; extra == "dev"
Requires-Dist: mock; extra == "dev"
Requires-Dist: pytz; extra == "dev"
Requires-Dist: django-filter>=22.1; extra == "dev"
Requires-Dist: pytest-django>=4.5.2; extra == "dev"
Dynamic: license-file
